gls_connector/__init__.py
gls_connector/gls_connector.py
gls_connector/gls_connector_tests.py
gls_connector-0.1.2.dist-info/LICENSE
gls_connector-0.1.2.dist-info/METADATA
gls_connector-0.1.2.dist-info/WHEEL
gls_connector-0.1.2.dist-info/top_level.txt
gls_connector-0.1.2.dist-info/RECORD
